{"updatedAt":"2026-03-31T13:25:38.277Z","createdAt":"2026-02-02T18:35:00.886Z","id":"XDIGgwe6jLIw77mr","name":"Reporte de horas intervals","active":false,"isArchived":false,"nodes":[{"parameters":{"content":"El cron se ejecuta cada día viernes a las 09 AM a correso de test","height":96,"width":166,"color":3},"type":"n8n-nodes-base.stickyNote","typeVersion":1,"position":[-688,-368],"id":"f0dd6048-2876-4044-90fc-a164202775a9","name":"Sticky Note2","disabled":true},{"parameters":{"content":"Calcula los días laborales del período y las horas esperadas de Lunes a Jueves y los Viernes.","height":112,"width":176},"type":"n8n-nodes-base.stickyNote","typeVersion":1,"position":[144,-416],"id":"e78bec8f-fbba-4433-af1f-9d0ad5cc434e","name":"Sticky Note4","disabled":true},{"parameters":{"content":"Consolida horas esperadas vs. horas ingresadas, calcula diferencias, porcentaje de cumplimiento, clasifica los resultado para asi consolidarlos en el HTML","height":128,"width":230,"color":5},"type":"n8n-nodes-base.stickyNote","typeVersion":1,"position":[80,-32],"id":"9c3754ce-6ba9-4ba2-a7e0-2af2bca438f2","name":"Sticky Note6","disabled":true},{"parameters":{"content":"El cron se ejecuta cada día viernes a las 12PM","height":96,"width":166,"color":3},"type":"n8n-nodes-base.stickyNote","typeVersion":1,"position":[-640,256],"id":"a9bbbc12-5385-4216-aa5c-5c0007877b82","name":"Sticky Note8"},{"parameters":{"jsCode":"const hoy = new Date();\nhoy.setMinutes(hoy.getMinutes() + hoy.getTimezoneOffset() + 180);\n\nconst fechaFin = new Date(hoy);\nfechaFin.setDate(fechaFin.getDate() - 1);\nwhile (fechaFin.getDay() === 0 || fechaFin.getDay() === 6) {\n  fechaFin.setDate(fechaFin.getDate() - 1);\n}\n\nconst fechaInicio = new Date(fechaFin.getFullYear(), fechaFin.getMonth(), 0);\nwhile (fechaInicio.getDay() !== 5) {\n  fechaInicio.setDate(fechaInicio.getDate() - 1);\n}\n\nconst MESES = ['enero','febrero','marzo','abril','mayo','junio','julio','agosto','septiembre','octubre','noviembre','diciembre'];\n\nconst inicioTexto = String(fechaInicio.getDate()).padStart(2,'0') + ' de ' + MESES[fechaInicio.getMonth()];\nconst finTexto = String(fechaFin.getDate()).padStart(2,'0') + ' de ' + MESES[fechaFin.getMonth()];\nconst periodoTexto = `${inicioTexto} – ${finTexto}`;\nconst mesCurso = MESES[fechaFin.getMonth()].toUpperCase().slice(0,3);\n\nconst personas = [\n  { personId:354371,nombre:'Susana',apellidoP:'Vásquez',apellidoM:'',area:'Contenido' },\n  { personId:429092,nombre:'Ana',apellidoP:'Saavedra',apellidoM:'',area:'Operaciones' },\n  { personId:425398,nombre:'Guillermo',apellidoP:'Salgado',apellidoM:'',area:'Dl Personas' },\n  { personId:371924,nombre:'José',apellidoP:'Valdés',apellidoM:'',area:'Dl Innova' },\n  { personId:426503,nombre:'Jose',apellidoP:'Silva',apellidoM:'Díaz',area:'Dl Innova' },\n  { personId:281553,nombre:'David',apellidoP:'Gómez',apellidoM:'',area:'Contenido' },\n  { personId:197714,nombre:'Valeska',apellidoP:'Villagrán',apellidoM:'',area:'Dl Innova' },\n  { personId:358826,nombre:'Rodrigo',apellidoP:'Retamal',apellidoM:'',area:'Dl Innova' },\n  { personId:411315,nombre:'Evelin',apellidoP:'Romero',apellidoM:'',area:'Dl Innova' },\n  { personId:423565,nombre:'Anai',apellidoP:'Ormazabal',apellidoM:'',area:'Dl Innova' },\n  { personId:362604,nombre:'Freddys',apellidoP:'Rojas',apellidoM:'',area:'Dl Innova' },\n  { personId:356965,nombre:'Margarita',apellidoP:'Olmedo',apellidoM:'',area:'Dl Innova' },\n  { personId:408021,nombre:'Carlos',apellidoP:'Martínez',apellidoM:'',area:'Dl Innova' },\n  { personId:425281,nombre:'Andres',apellidoP:'Yelpi',apellidoM:'',area:'Dl Innova' },\n  { personId:357713,nombre:'Yosbel',apellidoP:'Calvaire',apellidoM:'',area:'Dl Innova' },\n  { personId:357119,nombre:'Cristina',apellidoP:'Soto',apellidoM:'',area:'Marketing' },\n  { personId:427998,nombre:'Emily',apellidoP:'Ramírez',apellidoM:'',area:'Dl Innova' },\n  { personId:425282,nombre:'Edwuard',apellidoP:'Graterol',apellidoM:'',area:'Dl Innova' },\n  { personId:392742,nombre:'María Jose',apellidoP:'Vega',apellidoM:'',area:'Dl Innova' },\n  { personId:372821,nombre:'José',apellidoP:'Tapia',apellidoM:'',area:'Operaciones' },\n  { personId:383182,nombre:'Ariadna',apellidoP:'Landa',apellidoM:'',area:'Dl Innova' },\n  { personId:323747,nombre:'Joan',apellidoP:'de las Pozas',apellidoM:'',area:'Dl Innova' },\n  { personId:382778,nombre:'Fabiola',apellidoP:'Gonzáles',apellidoM:'',area:'Operaciones' },\n  { personId:411316,nombre:'José',apellidoP:'T.',apellidoM:'Leyva',area:'Dl Innova' },\n  { personId:425801,nombre:'Gladys',apellidoP:'González',apellidoM:'Torres',area:'Dl Innova' },\n  { personId:423566,nombre:'Daniel',apellidoP:'Contador',apellidoM:'Bustos',area:'Dl Innova' },\n  { personId:424256,nombre:'Osvaldo',apellidoP:'Fuentes',apellidoM:'',area:'Dl Innova' },\n  { personId:348504,nombre:'Carolina',apellidoP:'Gajardo',apellidoM:'',area:'Operaciones' },\n  { personId:357120,nombre:'Rodrigo',apellidoP:'Ruiz',apellidoM:'',area:'Marketing' },\n  { personId:428509,nombre:'Beatriz',apellidoP:'Quilodrán',apellidoM:'',area:'Dl Personas' }\n];\n\nreturn {\n  fechaInicio: fechaInicio.toISOString().slice(0,10),\n  fechaFin: fechaFin.toISOString().slice(0,10),\n  periodoTexto,\n  mesCurso,\n  personas\n};\n"},"type":"n8n-nodes-base.code","typeVersion":2,"position":[-80,-288],"id":"83ae8b89-91a3-44c1-a353-cf401ed8d825","name":"Repositorio1"},{"parameters":{"jsCode":"const repo = $input.first().json;\nconst inicio = new Date(repo.fechaInicio);\nconst fin = new Date(repo.fechaFin);\n\nlet diasLaborables = 0;\nlet horasTotales = 0;\n\nfor (let d = new Date(inicio); d <= fin; d.setDate(d.getDate() + 1)) {\n  const dia = d.getDay();\n  if (dia >= 1 && dia <= 4) { diasLaborables++; horasTotales += 8; }\n  else if (dia === 5) { diasLaborables++; horasTotales += 6.5; }\n}\n\nreturn {\n  json: {\n    diasLaborables,\n    horasTotales: +horasTotales.toFixed(1),\n    personas: repo.personas,\n    mesCurso: repo.mesCurso,\n    fechaInicio: repo.fechaInicio,\n    fechaFin: repo.fechaFin,\n    periodoTexto: repo.periodoTexto\n  }\n};"},"type":"n8n-nodes-base.code","typeVersion":2,"position":[144,-288],"id":"666848af-f93b-4373-966a-550d102e4636","name":"Calculo de horas1"},{"parameters":{"url":"=https://api.myintervals.com/time/?datebegin={{$json.fechaInicio}}&dateend={{$json.fechaFin}}&limit=5000","authentication":"genericCredentialType","genericAuthType":"httpBasicAuth","options":{"response":{"response":{}}}},"type":"n8n-nodes-base.httpRequest","typeVersion":4.3,"position":[368,-288],"id":"2eeddbee-6345-43dd-b228-63443cb90557","name":"HTTP Request1","credentials":{"httpBasicAuth":{"id":"hd5ZkGI3m1uNQVbw","name":"intervals"}}},{"parameters":{"jsCode":"const apiData = $input.first().json;\nconst registros = apiData.time || [];\n\nconst calc2 = $('Calculo de horas1').first().json;\nconst personasArray = calc2.personas;\nconst diasLaborables = calc2.diasLaborables;\nconst horasEsperadas = calc2.horasTotales;\nconst mesCurso = calc2.mesCurso;\n\nconst horasPorPersona = {};\nfor (const r of registros) {\n  const pid = Number(r.personid);\n  horasPorPersona[pid] = (horasPorPersona[pid] || 0) + Number(r.time || 0);\n}\n\nconst resultados = personasArray.map(p => {\n  const nombre = `${p.nombre} ${p.apellidoP} ${p.apellidoM || ''}`.trim();\n  const horasIngresadas = +(horasPorPersona[p.personId] || 0).toFixed(1);\n  const diferencia = +(horasEsperadas - horasIngresadas).toFixed(1);\n  const porcentaje = horasEsperadas > 0 ? Math.round((horasIngresadas / horasEsperadas) * 100) : 0;\n  const estado = porcentaje >= 100 ? '✅ Al día' : porcentaje >= 80 ? '⚠️ Pendiente' : '❌ Atrasado';\n\n  return {\n    Area: p.area,\n    Nombre: nombre,\n    horasEsperadas: +horasEsperadas.toFixed(1),\n    horasIngresadas,\n    diferencia,\n    semanasPendientes: diferencia > 0 ? +((diferencia / 40).toFixed(1)) : 0,\n    porcentaje,\n    estado,\n    mesCurso,\n    diasLaborables\n  };\n});\n\nreturn resultados.sort((a, b) => a.diferencia - b.diferencia);"},"type":"n8n-nodes-base.code","typeVersion":2,"position":[-48,-80],"id":"796a7c59-2e4d-471f-9975-c6aba950f425","name":"Resultados1"},{"parameters":{"jsCode":"const datos = $input.all();\nconst calc = $('Calculo de horas1').first().json;\n\nconst periodoInicio = calc.fechaInicio;\nconst periodoFin = calc.fechaFin;\nconst diasLaborables = datos.length ? datos[0].json.diasLaborables : 0;\nconst horasEsperadasPeriodo = datos.length ? datos[0].json.horasEsperadas : 0;\nconst totalColaboradores = datos.length;\n\nconst alDia = datos.filter(i => i.json.estado === '✅ Al día').length;\nconst pendientes = datos.filter(i => i.json.estado === '⚠️ Pendiente').length;\nconst atrasados = datos.filter(i => i.json.estado === '❌ Atrasado').length;\n\nconst htmlCompleto = `\n<!DOCTYPE html>\n<html>\n<head><meta charset=\"UTF-8\"></head>\n<body style=\"margin:0;padding:8px 10px;font-family:Arial,APTOS,sans-serif;font-size:12px;\">\n\n<h2 style=\"color:#7049BC;font-size:14px;margin:0;\">\n  <strong>Reporte de Horas – ${datos[0]?.json.mesCurso || ''}</strong>\n</h2>\n\n<p style=\"margin:8px 0;\">Estimad@s, esperamos que este mensaje les encuentre bien:</p>\n\n<p style=\"margin:8px 0;\">Como formalidad semanal, se comparte el reporte de ingreso de horas correspondiente\nal período entre las fechas: <strong>${calc.periodoTexto}</strong>.</p>\n\n<p style=\"margin:12px 0;\">\n  <span style=\"display:inline-block;background:#5CDB82;padding:10px;color:#000;\">\n    <strong>Nota:</strong> al momento de registrar las horas y su respectiva descripción,\n    se solicita no utilizar signos especiales (como \", &, %, entre otros),\n    ya que estos afectan la reportería.\n  </span>\n</p>\n\n<table width=\"100%\" cellpadding=\"0\" cellspacing=\"0\" border=\"1\" bordercolor=\"#5838A3\"\n  style=\"width:100%;max-width:900px;border-collapse:collapse;font-size:12px;margin-top:15px;text-align:center;\">\n<thead><tr>\n  ${['Área','Colaborador','Horas Esperadas','Horas Ingresadas','Diferencia','Porcentaje','Estado','Semanas Pendientes'].map(h =>\n    `<th bgcolor=\"#7049BC\" style=\"border:1px solid #5838A3;color:#ffffff;padding:6px 4px;font-weight:bold;text-align:center;vertical-align:middle;\">${h}</th>`\n  ).join('')}\n</tr></thead>\n<tbody>\n${datos.map(d => {\n  const colorFila = d.json.estado === '✅ Al día' ? '#C9D6CC' : d.json.estado === '⚠️ Pendiente' ? '#E8DFC7' : '#F4CCCC';\n  const colorBorde = d.json.estado === '✅ Al día' ? '#8BA88F' : d.json.estado === '⚠️ Pendiente' ? '#D4BC8E' : '#E89A9A';\n  const td = (val, bold=false) => `<td bgcolor=\"${colorFila}\" style=\"padding:0;height:18px;line-height:18px;vertical-align:middle;text-align:center;border:1px solid ${colorBorde};\">${bold ? `<strong>${val}</strong>` : val}</td>`;\n  return `<tr>\n    ${td(d.json.Area)}\n    ${td(d.json.Nombre, true)}\n    ${td(d.json.horasEsperadas, true)}\n    ${td(d.json.horasIngresadas, true)}\n    ${td(Math.abs(d.json.diferencia))}\n    ${td(d.json.porcentaje + '%')}\n    ${td(d.json.estado, true)}\n    ${td(d.json.semanasPendientes)}\n  </tr>`;\n}).join('')}\n</tbody></table>\n\n<p style=\"color:#7049BC;font-weight:bold;margin-top:18px;font-size:14px;\">Alcances del Reporte:</p>\n<ul style=\"margin:0;padding-left:18px;\">\n  <li><strong>Fecha inicio:</strong> ${periodoInicio}</li>\n  <li><strong>Fecha fin:</strong> ${periodoFin}</li>\n  <li><strong>Días hábiles considerados:</strong> ${diasLaborables}</li>\n  <li><strong>Cantidad de horas contabilizadas en el mes:</strong> ${horasEsperadasPeriodo}</li>\n  <li><strong>Total colaboradores:</strong> ${totalColaboradores}</li>\n  <li><strong>Colaboradores al día:</strong> ${alDia}</li>\n  <li><strong>Colaboradores pendientes:</strong> ${pendientes}</li>\n  <li><strong>Colaboradores atrasados:</strong> ${atrasados}</li>\n</ul>\n\n<p style=\"margin-top:16px;\">Frente a dudas, consultas o validación de métricas, comunicarse directamente\ncon el <strong>área de control de gestión</strong>.</p>\n\n<p style=\"margin-top:14px;\">Saludos cordiales.<br>Equipo de Infraestructura.</p>\n\n</body></html>\n`;\n\nreturn { htmlContent: htmlCompleto };"},"type":"n8n-nodes-base.code","typeVersion":2,"position":[336,-80],"id":"9c493fcf-7253-4934-ad38-516b636a50db","name":"HTML1"},{"parameters":{"fromEmail":"info@n8n.notificadl.cl","toEmail":"={{ $json.remitentes }}","subject":"=Reporte de ingreso de horas en intervals","text":"=","html":"={{$json.htmlContent}}","attachments":"="},"type":"n8n-nodes-base.mailgun","typeVersion":1,"position":[528,192],"id":"51e86dee-61b4-47a2-a1e8-a38bd56618c6","name":"Mailgun_Call1","credentials":{"mailgunApi":{"id":"jXQjjlGEuBBpD3Wo","name":"Mailgun account 4"}}},{"parameters":{"rule":{"interval":[{"field":"cronExpression","expression":"0 0 12 * * 5"}]}},"type":"n8n-nodes-base.scheduleTrigger","typeVersion":1.3,"position":[-784,0],"id":"a9d12d35-6698-4b37-99da-f06e56cc05e7","name":"Cron semanal días viernes1","disabled":true},{"parameters":{"rule":{"interval":[{"field":"cronExpression","expression":"0 0 11 * * 5"}]}},"type":"n8n-nodes-base.scheduleTrigger","typeVersion":1.3,"position":[-784,-176],"id":"7ae80d75-2252-4498-ac0b-7cf2e1e67751","name":"Cron semanal días viernes(TEST)1","disabled":true},{"parameters":{"mode":"raw","jsonOutput":"{\n  \"remitentes\": \"ayelpi@dl.cl, cchavez@dl.cl, svidal@dl.cl, jsilva@dl.cl, jvaldesh@dl.cl , jdelaspozas@dl.cl \"\n}","options":{}},"type":"n8n-nodes-base.set","typeVersion":3.4,"position":[-528,-176],"id":"3d59be5a-a59e-404f-99ba-95da52548e6e","name":"emails1"},{"parameters":{"assignments":{"assignments":[{"id":"1be7a60b-5545-4610-b5ce-c73cc5fb0a3d","name":"remitentes","value":"ymartinez@dl.cl, jdelaspozas@dl.cl, jvaldesh@dl.cl, ayelpi@dl.cl, cchavez@dl.cl, svidal@dl.cl, jsilva@dl.cl, hrivas@dl.cl","type":"string"}]},"options":{}},"type":"n8n-nodes-base.set","typeVersion":3.4,"position":[-528,0],"id":"58412f12-e293-4053-b2d9-efb029bd6dec","name":"email1"},{"parameters":{"mode":"combine","combineBy":"combineByPosition","options":{}},"type":"n8n-nodes-base.merge","typeVersion":3.2,"position":[-64,192],"id":"13ce5040-c950-4687-8fe4-abd684b405c5","name":"Merge1"}],"connections":{"Repositorio1":{"main":[[{"node":"Calculo de horas1","type":"main","index":0}]]},"Calculo de horas1":{"main":[[{"node":"HTTP Request1","type":"main","index":0}]]},"HTTP Request1":{"main":[[{"node":"Resultados1","type":"main","index":0}]]},"Resultados1":{"main":[[{"node":"HTML1","type":"main","index":0}]]},"HTML1":{"main":[[{"node":"Merge1","type":"main","index":0}]]},"Cron semanal días viernes1":{"main":[[{"node":"email1","type":"main","index":0}]]},"Cron semanal días viernes(TEST)1":{"main":[[{"node":"emails1","type":"main","index":0}]]},"emails1":{"main":[[{"node":"Repositorio1","type":"main","index":0},{"node":"Merge1","type":"main","index":1}]]},"email1":{"main":[[{"node":"Repositorio1","type":"main","index":0},{"node":"Merge1","type":"main","index":1}]]},"Merge1":{"main":[[{"node":"Mailgun_Call1","type":"main","index":0}]]}},"settings":{"executionOrder":"v1","availableInMCP":false,"timeSavedMode":"fixed","timezone":"America/Santiago","callerPolicy":"workflowsFromSameOwner","binaryMode":"separate"},"staticData":{"node:Cron semanal días viernes":{"recurrenceRules":[]},"node:Schedule Trigger":{"recurrenceRules":[]},"node:Cron para pruebas":{"recurrenceRules":[]},"node:Cron semanal días viernes(TEST)":{"recurrenceRules":[]},"node:cron1":{"recurrenceRules":[]},"node:cron":{"recurrenceRules":[]},"node:Cron semanal días viernes1":{"recurrenceRules":[]},"node:Cron semanal días viernes(TEST)1":{"recurrenceRules":[]}},"meta":{"templateCredsSetupCompleted":true},"pinData":{},"versionId":"99939474-84e0-41b3-9934-272d9085450c","activeVersionId":null,"triggerCount":2,"shared":[{"updatedAt":"2026-02-02T18:35:00.886Z","createdAt":"2026-02-02T18:35:00.886Z","role":"workflow:owner","workflowId":"XDIGgwe6jLIw77mr","projectId":"iYcETjaBCKTmmaOx"}],"activeVersion":null,"tags":[]}